alerts_in_ua/__init__.py
alerts_in_ua/air_raid_alert_oblast_status.py
alerts_in_ua/air_raid_alert_oblast_statuses.py
alerts_in_ua/alert.py
alerts_in_ua/alerts.py
alerts_in_ua/async_client.py
alerts_in_ua/client.py
alerts_in_ua/errors.py
alerts_in_ua/location_uid_resolver.py
alerts_in_ua/ua_date_parser.py
alerts_in_ua/user_agent.py
alerts_in_ua-0.2.7.dist-info/LICENSE.txt
alerts_in_ua-0.2.7.dist-info/METADATA
alerts_in_ua-0.2.7.dist-info/WHEEL
alerts_in_ua-0.2.7.dist-info/top_level.txt
alerts_in_ua-0.2.7.dist-info/RECORD
